{
  "races": [
    {
      "date": "20250221",
      "location": "서울",
      "raceNumber": 6,
      "videoType": "y",
      "language": "kor",
      "videoId": "https://youtu.be/6BK5BU-W360"
    },
    {
      "date": "20250222",
      "location": "서울",
      "raceNumber": 9,
      "videoType": "y",
      "language": "kor",
      "videoId": "https://youtu.be/xlRwKUHIDvQ"
    },
    {
      "date": "20250222",
      "location": "서울",
      "raceNumber": 9,
      "videoType": "r",
      "language": "kor",
      "videoId": "https://youtu.be/3ERQC52I2cU"
    },
    {
      "date": "20250222",
      "location": "SEOUL",
      "raceNumber": 9,
      "videoType": "r",
      "language": "eng",
      "videoId": "https://youtu.be/MZf0Ce_E3JE"
    },
    {
      "date": "20250222",
      "location": "서울",
      "raceNumber": 10,
      "videoType": "y",
      "language": "kor",
      "videoId": "https://youtu.be/uDV7CmfHi6A"
    },
    {
      "date": "20250222",
      "location": "서울",
      "raceNumber": 10,
      "videoType": "r",
      "language": "kor",
      "videoId": "https://youtu.be/WJGe0Gd0tBk"
    },
    {
      "date": "20250222",
      "location": "SEOUL",
      "raceNumber": 10,
      "videoType": "r",
      "language": "eng",
      "videoId": "https://youtu.be/G0HJJrium8g"
    },
    {
      "date": "20250222",
      "location": "서울",
      "raceNumber": 11,
      "videoType": "y",
      "language": "kor",
      "videoId": "https://youtu.be/SwfsMLhVDeU"
    }
  ]
}